epub2text/__init__.py
epub2text/__main__.py
epub2text/_version.py
epub2text/bookmarks.py
epub2text/cleaner.py
epub2text/cli.py
epub2text/formatters.py
epub2text/models.py
epub2text/parser.py
epub2text/py.typed
epub2text/reader.py
epub2text-0.2.0.dist-info/licenses/LICENSE
epub2text-0.2.0.dist-info/METADATA
epub2text-0.2.0.dist-info/WHEEL
epub2text-0.2.0.dist-info/entry_points.txt
epub2text-0.2.0.dist-info/top_level.txt
epub2text-0.2.0.dist-info/RECORD
