Metadata-Version: 2.4
Name: epub2text
Version: 0.2.0
Summary: A simple tool to extract text from EPUB files.
Author-email: Holger Nahrstaedt <nahrstaedt@gmail.com>
License: MIT License
Project-URL: Homepage, https://github.com/holgern/epub2text
Classifier: Intended Audience :: Developers
Classifier: License :: OSI Approved :: MIT License
Classifier: Operating System :: OS Independent
Classifier: Programming Language :: Python :: 3
Classifier: Programming Language :: Python :: 3.9
Classifier: Programming Language :: Python :: 3.10
Classifier: Programming Language :: Python :: 3.11
Classifier: Programming Language :: Python :: 3.12
Classifier: Programming Language :: Python :: 3.13
Classifier: Programming Language :: Python :: 3.14
Classifier: Topic :: Software Development :: Libraries
Requires-Python: >=3.9
License-File: LICENSE
Requires-Dist: click>=8.0.0
Requires-Dist: rich>=13.0.0
Requires-Dist: ebooklib>=0.18
Requires-Dist: beautifulsoup4>=4.12.0
Requires-Dist: phrasplit>=0.1.0
Provides-Extra: lxml
Requires-Dist: lxml>=4.9.0; extra == "lxml"
Provides-Extra: dev
Requires-Dist: pytest>=7.0.0; extra == "dev"
Requires-Dist: ruff>=0.1.0; extra == "dev"
Dynamic: license-file
